[{"id":1,"nombre_producto":"Daniella Iwanowski","imagen":"producto_1.jpg","categoria":"M","marca":"LX","medida":336,"outlet":"y","precio":"$9683.75"},
{"id":2,"nombre_producto":"Belia Yeld","imagen":"producto_2.jpg","categoria":"M","marca":"E-Series","medida":167,"outlet":"n","precio":"$19589.50"},
{"id":3,"nombre_producto":"Candi Callar","imagen":"producto_3.jpg","categoria":"M","marca":"Maxima","medida":349,"outlet":"n","precio":"$5404.38"},
{"id":4,"nombre_producto":"Sylvia Overstone","imagen":"producto_4.jpg","categoria":"M","marca":"XJ Series","medida":8,"outlet":"n","precio":"$7541.22"},
{"id":5,"nombre_producto":"Erl Simononsky","imagen":"producto_5.jpg","categoria":"M","marca":"A5","medida":309,"outlet":"n","precio":"$10689.74"},
{"id":6,"nombre_producto":"Abel Donoher","imagen":"producto_6.jpg","categoria":"M","marca":"Freelander","medida":178,"outlet":"n","precio":"$17029.19"},
{"id":7,"nombre_producto":"Anabelle Pitbladdo","imagen":"producto_7.jpg","categoria":"M","marca":"Panamera","medida":218,"outlet":"n","precio":"$857.88"},
{"id":8,"nombre_producto":"Tyrone Hubner","imagen":"producto_8.jpg","categoria":"M","marca":"Malibu","medida":166,"outlet":"n","precio":"$8011.02"},
{"id":9,"nombre_producto":"Evita Aland","imagen":"producto_9.jpg","categoria":"M","marca":"4Runner","medida":420,"outlet":"y","precio":"$16628.17"},
{"id":10,"nombre_producto":"Rolph Shrimpling","imagen":"producto_10.jpg","categoria":"M","marca":"MKZ","medida":457,"outlet":"y","precio":"$18260.49"},
{"id":11,"nombre_producto":"Dallis Duinbleton","imagen":"producto_11.jpg","categoria":"M","marca":"Typ-1","medida":56,"outlet":"n","precio":"$8243.35"},
{"id":12,"nombre_producto":"Gerri Coogan","imagen":"producto_12.jpg","categoria":"M","marca":"Ram Van 3500","medida":199,"outlet":"n","precio":"$3210.05"},
{"id":13,"nombre_producto":"Guglielmo Queen","imagen":"producto_13.jpg","categoria":"M","marca":"TT","medida":154,"outlet":"n","precio":"$7104.74"},
{"id":14,"nombre_producto":"Jarrid Bean","imagen":"producto_14.jpg","categoria":"M","marca":"S10","medida":215,"outlet":"n","precio":"$19457.55"},
{"id":15,"nombre_producto":"Olly Suermeiers","imagen":"producto_15.jpg","categoria":"M","marca":"Altima","medida":151,"outlet":"n","precio":"$9639.31"},
{"id":16,"nombre_producto":"Charlene Jouannisson","imagen":"producto_16.jpg","categoria":"F","marca":"Equinox","medida":367,"outlet":"y","precio":"$19359.97"},
{"id":17,"nombre_producto":"Babb Kleinsmuntz","imagen":"producto_17.jpg","categoria":"F","marca":"370Z","medida":191,"outlet":"n","precio":"$13038.62"},
{"id":18,"nombre_producto":"Cathee Bonnick","imagen":"producto_18.jpg","categoria":"F","marca":"Grand Caravan","medida":498,"outlet":"n","precio":"$6282.55"},
{"id":19,"nombre_producto":"Ashley Lowy","imagen":"producto_19.jpg","categoria":"F","marca":"Taurus","medida":219,"outlet":"n","precio":"$6533.40"},
{"id":20,"nombre_producto":"Koralle Veryard","imagen":"producto_20.jpg","categoria":"F","marca":"Mustang","medida":280,"outlet":"n","precio":"$633.22"},
{"id":21,"nombre_producto":"Allie Stollenbecker","imagen":"producto_21.jpg","categoria":"F","marca":"Grand Am","medida":412,"outlet":"n","precio":"$10382.66"},
{"id":22,"nombre_producto":"Harrison Cowl","imagen":"producto_22.jpg","categoria":"F","marca":"V70","medida":140,"outlet":"n","precio":"$7895.01"},
{"id":23,"nombre_producto":"Annamaria Ickovicz","imagen":"producto_23.jpg","categoria":"F","marca":"B-Series Plus","medida":310,"outlet":"n","precio":"$13977.84"},
{"id":24,"nombre_producto":"Adriane De Giovanni","imagen":"producto_24.jpg","categoria":"F","marca":"S-Class","medida":352,"outlet":"n","precio":"$15919.09"},
{"id":25,"nombre_producto":"Nathanil Fantham","imagen":"producto_25.jpg","categoria":"F","marca":"300C","medida":438,"outlet":"n","precio":"$6458.94"},
{"id":26,"nombre_producto":"Charlton Glasgow","imagen":"producto_26.jpg","categoria":"F","marca":"LeBaron","medida":281,"outlet":"y","precio":"$14751.73"},
{"id":27,"nombre_producto":"Craggy Matyasik","imagen":"producto_27.jpg","categoria":"F","marca":"500E","medida":144,"outlet":"y","precio":"$2906.63"},
{"id":28,"nombre_producto":"Ana Betancourt","imagen":"producto_28.jpg","categoria":"F","marca":"Galant","medida":171,"outlet":"n","precio":"$10118.43"},
{"id":29,"nombre_producto":"Reuben Yude","imagen":"producto_29.jpg","categoria":"F","marca":"5000S","medida":205,"outlet":"n","precio":"$15195.20"},
{"id":30,"nombre_producto":"Deeann Elintune","imagen":"producto_30.jpg","categoria":"F","marca":"GS","medida":418,"outlet":"n","precio":"$2602.76"},
{"id":31,"nombre_producto":"Ulrica Collyer","imagen":"producto_31.jpg","categoria":"F","marca":"QX56","medida":312,"outlet":"n","precio":"$16842.25"},
{"id":32,"nombre_producto":"Sauveur Naismith","imagen":"producto_32.jpg","categoria":"F","marca":"RX-7","medida":397,"outlet":"n","precio":"$3094.74"},
{"id":33,"nombre_producto":"Morganne Merrick","imagen":"producto_33.jpg","categoria":"F","marca":"Element","medida":366,"outlet":"n","precio":"$8950.92"},
{"id":34,"nombre_producto":"Stella Bunyard","imagen":"producto_34.jpg","categoria":"F","marca":"Santa Fe","medida":385,"outlet":"n","precio":"$1318.65"},
{"id":35,"nombre_producto":"Katinka Filippozzi","imagen":"producto_35.jpg","categoria":"F","marca":"Mustang","medida":475,"outlet":"n","precio":"$9914.17"},
{"id":36,"nombre_producto":"Nessa Battleson","imagen":"producto_36.jpg","categoria":"F","marca":"E-Series","medida":342,"outlet":"n","precio":"$2896.65"},
{"id":37,"nombre_producto":"Artus Lemar","imagen":"producto_37.jpg","categoria":"F","marca":"del Sol","medida":267,"outlet":"y","precio":"$9126.08"},
{"id":38,"nombre_producto":"Felisha Scorah","imagen":"producto_38.jpg","categoria":"F","marca":"GT500","medida":34,"outlet":"y","precio":"$6188.67"},
{"id":39,"nombre_producto":"Shana Turley","imagen":"producto_39.jpg","categoria":"F","marca":"Vega","medida":386,"outlet":"y","precio":"$10637.50"},
{"id":40,"nombre_producto":"Korney Vahl","imagen":"producto_40.jpg","categoria":"F","marca":"Sebring","medida":63,"outlet":"n","precio":"$10623.47"},
{"id":41,"nombre_producto":"Steffane Hendron","imagen":"producto_41.jpg","categoria":"F","marca":"LS Hybrid","medida":130,"outlet":"n","precio":"$9973.32"},
{"id":42,"nombre_producto":"Bartholomew Skey","imagen":"producto_42.jpg","categoria":"F","marca":"riolet","medida":320,"outlet":"n","precio":"$3076.01"},
{"id":43,"nombre_producto":"Kasey Wakeham","imagen":"producto_43.jpg","categoria":"F","marca":"Typ-1","medida":434,"outlet":"n","precio":"$1566.27"},
{"id":44,"nombre_producto":"Editha Christofe","imagen":"producto_44.jpg","categoria":"F","marca":"Coachbuilder","medida":485,"outlet":"n","precio":"$8437.91"},
{"id":45,"nombre_producto":"Leia Erdis","imagen":"producto_45.jpg","categoria":"F","marca":"Hombre","medida":445,"outlet":"n","precio":"$9885.93"},
{"id":46,"nombre_producto":"Wendi Lionel","imagen":"producto_46.jpg","categoria":"F","marca":"Sedona","medida":277,"outlet":"n","precio":"$6034.15"},
{"id":47,"nombre_producto":"Jeffrey Lanchester","imagen":"producto_47.jpg","categoria":"F","marca":"F150","medida":295,"outlet":"n","precio":"$1765.81"},
{"id":48,"nombre_producto":"Bellina Belderfield","imagen":"producto_48.jpg","categoria":"F","marca":"Ranger","medida":385,"outlet":"y","precio":"$11720.20"},
{"id":49,"nombre_producto":"Giorgia Halksworth","imagen":"producto_49.jpg","categoria":"F","marca":"Vision","medida":327,"outlet":"n","precio":"$18278.24"},
{"id":50,"nombre_producto":"Kirbee Iacobacci","imagen":"producto_50.jpg","categoria":"F","marca":"Integra","medida":247,"outlet":"n","precio":"$18744.96"},
{"id":51,"nombre_producto":"Beverlie Casper","imagen":"producto_51.jpg","categoria":"F","marca":"Genesis","medida":108,"outlet":"y","precio":"$8181.98"},
{"id":52,"nombre_producto":"Klement Ellick","imagen":"producto_52.jpg","categoria":"U","marca":"Sierra","medida":342,"outlet":"y","precio":"$12264.51"},
{"id":53,"nombre_producto":"Lin Merryweather","imagen":"producto_53.jpg","categoria":"U","marca":"Caliber","medida":358,"outlet":"n","precio":"$10848.73"},
{"id":54,"nombre_producto":"Ottilie Stuttard","imagen":"producto_54.jpg","categoria":"U","marca":"Cooper","medida":236,"outlet":"y","precio":"$883.09"},
{"id":55,"nombre_producto":"Sargent Heinzler","imagen":"producto_55.jpg","categoria":"U","marca":"Cougar","medida":307,"outlet":"n","precio":"$11514.39"},
{"id":56,"nombre_producto":"Francine McIlvenny","imagen":"producto_56.jpg","categoria":"U","marca":"Grand Prix","medida":464,"outlet":"n","precio":"$15161.73"},
{"id":57,"nombre_producto":"Freddi Scandroot","imagen":"producto_57.jpg","categoria":"U","marca":"Cutlass Supreme","medida":438,"outlet":"n","precio":"$5360.38"},
{"id":58,"nombre_producto":"Fletch Trassler","imagen":"producto_58.jpg","categoria":"U","marca":"Suburban 1500","medida":188,"outlet":"n","precio":"$1762.90"},
{"id":59,"nombre_producto":"Cassaundra Grunwald","imagen":"producto_59.jpg","categoria":"U","marca":"Titan","medida":216,"outlet":"n","precio":"$5345.22"},
{"id":60,"nombre_producto":"Marthe Castelletti","imagen":"producto_60.jpg","categoria":"U","marca":"Concorde","medida":166,"outlet":"n","precio":"$12378.96"},
{"id":61,"nombre_producto":"Salomo Twallin","imagen":"producto_61.jpg","categoria":"U","marca":"A6","medida":364,"outlet":"n","precio":"$12972.72"},
{"id":62,"nombre_producto":"Glad Tarbet","imagen":"producto_62.jpg","categoria":"U","marca":"Caravan","medida":388,"outlet":"n","precio":"$13792.85"},
{"id":63,"nombre_producto":"Neil Ginity","imagen":"producto_63.jpg","categoria":"U","marca":"Crown Victoria","medida":448,"outlet":"n","precio":"$13145.60"},
{"id":64,"nombre_producto":"Page Lettsom","imagen":"producto_64.jpg","categoria":"U","marca":"Seville","medida":217,"outlet":"n","precio":"$17527.46"},
{"id":65,"nombre_producto":"Gram Renn","imagen":"producto_65.jpg","categoria":"U","marca":"Gran Sport","medida":424,"outlet":"n","precio":"$4991.78"},
{"id":66,"nombre_producto":"Ardeen Hasser","imagen":"producto_66.jpg","categoria":"U","marca":"960","medida":478,"outlet":"y","precio":"$3555.46"},
{"id":67,"nombre_producto":"Ingaborg McGrotty","imagen":"producto_67.jpg","categoria":"U","marca":"Eclipse","medida":294,"outlet":"y","precio":"$5603.22"},
{"id":68,"nombre_producto":"Odelle Gheorghie","imagen":"producto_68.jpg","categoria":"U","marca":"Ascender","medida":363,"outlet":"n","precio":"$4358.40"}]